{"cameraMode":{"drawMode":0,"name":"Shaded","section":"Shading Mode"},"sceneLighting":true,"audioPlay":false,"sceneViewState":{"m_AlwaysRefresh":false,"showFog":true,"showSkybox":true,"showFlares":true,"showImageEffects":true,"showParticleSystems":true,"showVisualEffectGraphs":true,"m_FxEnabled":true},"in2DMode":false,"pivot":{"x":69.91866302490235,"y":-11.874540328979493,"z":11.225598335266114},"rotation":{"x":0.05916876345872879,"y":0.6343125104904175,"z":-0.04886693134903908,"w":0.7693369388580322},"size":37.37828063964844,"orthographic":false}